kafka/__init__.py
kafka/artifacts.py
kafka/auth.py
kafka/client.py
kafka/config.py
kafka/errors.py
kafka/inference.py
kafka/progress.py
kafka/remote.py
kafka/sdk.py
kafka/storage.py
kafka/trainer.py
kafkalab/__init__.py
kafkalab-0.1.0.dist-info/licenses/LICENSE
kafkalab-0.1.0.dist-info/METADATA
kafkalab-0.1.0.dist-info/WHEEL
kafkalab-0.1.0.dist-info/top_level.txt
kafkalab-0.1.0.dist-info/RECORD
