Metadata-Version: 2.4
Name: kafkalab
Version: 0.1.0
Summary: Kafka Compute seeker SDK
License: Apache-2.0
Requires-Python: >=3.9
License-File: LICENSE
Dynamic: license-file
